cdtb/__init__.py
cdtb/__main__.py
cdtb/arenadata.py
cdtb/binfile.py
cdtb/data.py
cdtb/export.py
cdtb/hashes.py
cdtb/patcher.py
cdtb/rads.py
cdtb/rstfile.py
cdtb/sknfile.py
cdtb/storage.py
cdtb/tftdata.py
cdtb/tools.py
cdtb/wad.py
cdtb-1.2.0.dist-info/METADATA
cdtb-1.2.0.dist-info/WHEEL
cdtb-1.2.0.dist-info/entry_points.txt
cdtb-1.2.0.dist-info/licenses/LICENSE
cdtb-1.2.0.dist-info/RECORD
