Metadata-Version: 2.4
Name: cdtb
Version: 1.2.0
Summary: A toolbox to work with League of Legends game files
Project-URL: Homepage, https://communitydragon.org
Project-URL: Repository, https://github.com/CommunityDragon/CDTB
Author: CDragon team
License-File: LICENSE
Classifier: License :: OSI Approved :: GNU Lesser General Public License v3 (LGPLv3)
Classifier: Programming Language :: Python :: 3
Requires-Python: >=3.8
Requires-Dist: hachoir
Requires-Dist: pillow
Requires-Dist: pyzstd
Requires-Dist: requests
Requires-Dist: ujson
Requires-Dist: xxhash
Provides-Extra: tests
Requires-Dist: pytest; extra == 'tests'
Requires-Dist: pytest-mock; extra == 'tests'
